<?xml version="1.0" encoding="ISO-8859-1"?>
<BrandonMFong>
    <Directories>
        <Directory alias='main'>B:\</Directory>
        <Directory alias='code'>B:\CODE</Directory>
        <Directory alias='col'>B:\COLLEGE</Directory>
        <Directory alias='sc1920'>B:\COLLEGE\19_20</Directory>
        <Directory alias='f19'>B:\COLLEGE\19_20\Fall_19</Directory>
        <Directory alias='compe361'>B:\COLLEGE\19_20\Fall_19\CompE_361</Directory>
        <Directory alias='compe475'>B:\COLLEGE\19_20\Fall_19\Compe_475</Directory>
        <Directory alias='compe496a'>B:\COLLEGE\19_20\Fall_19\CompE_496A</Directory>
        <Directory alias='ee450'>B:\COLLEGE\19_20\Fall_19\EE_450</Directory>
        <Directory alias='ee420'>B:\COLLEGE\19_20\Fall_19\EE_420</Directory>
        <Directory alias='s20'>B:\COLLEGE\19_20\Spring_20</Directory>
        <Directory alias='compe565'>B:\COLLEGE\19_20\Spring_20\CompE_565</Directory>
        <Directory alias='ee600'>B:\COLLEGE\19_20\Spring_20\EE_600</Directory>
        <Directory alias='compe560'>B:\COLLEGE\19_20\Spring_20\CompE_560</Directory>
        <Directory alias='compe496b'>B:\COLLEGE\19_20\Spring_20\CompE_496B</Directory>
        <Directory alias='job'>B:\JOB</Directory>
        <Directory alias='li'>B:\LIFE</Directory>
        <Directory alias='mus'>B:\MUSIC</Directory>
        <Directory alias='pers'>B:\PERSONAL</Directory>
        <Directory alias='pic'>B:\PICTURES</Directory>
        <Directory alias='rec'>B:\RECYCLE</Directory>
        <Directory alias='Pow'>B:\Powershell</Directory>
        <Directory alias='si'>B:\SITES</Directory>
        <Directory alias='bf'>B:\SITES\BrandonFongMusic</Directory>
        <Directory alias='source'>B:\SOURCES</Directory>
        <Directory alias='repo'>B:\SOURCES\Repos</Directory>
        <Directory alias='yes'>B:\SOURCES\Repos\DualPowerGeneration</Directory>
        <Directory alias='dl'>B:\DOWNLOADS</Directory>
        <Directory alias='docs'>B:\DOCUMENTS</Directory>
        <Directory alias='one'>~\OneDrive</Directory>
        <Directory alias='c'>C:\</Directory>
        <Directory alias='cmain'>C:\Users\bfwan\Brandon.Fong\</Directory>
    </Directories>

    <!--[System.Xml.XmlElement]$d = (Select-Xml -path .\SCRIPTS\Config\User.xml -XPath "//Websites").Node -->
    <Objects>
        <Object VarName="User">
            <Gmail>https://mail.google.com/mail</Gmail>
            <Netflix>https://Netflix.com</Netflix>
            <Youtube>https://Youtube.com</Youtube>
            <Facebook>https://facebook.com</Facebook>
            <LinkedIn>
                <URL>https://www.linkedin.com/nhome/</URL>
                <Profile></Profile>
            </LinkedIn>
            <Git>https://github.com/BrandonMFong</Git>
            <GoogleDrive>https://drive.google.com/drive/u/0/my-drive</GoogleDrive>
            <DisneyPlus>https://www.disneyplus.com</DisneyPlus>
            <Hulu>https://www.hulu.com</Hulu>
            <Slack>https://dualpowergeneration.slack.com</Slack>
            <YES>https://dualpowergeneration.sdsu.edu</YES>
            <iCloud>https://www.icloud.com/</iCloud>
            <GoogleCloud>https://cloud.google.com</GoogleCloud>
            <Taxact>https://www.taxact.com/</Taxact>
            <StandardUserName>F139B118-40C4-4293-9A60-498FEA8AE1B7</StandardUserName>
            <Emails>
                <Personal>c4a21f9b-1376-41db-a7a6-4bbaf09e1dd8</Personal>
                <Professional>94edc712-0435-4574-80ad-fbb1aab3dc20</Professional>
                <Music>2508beb5-3958-48d5-931b-c7b55efa7c92</Music>
                <Work>340861de-d4f9-43a3-badd-d0945e3e392a</Work>
                <Old>21a540d4-4818-404a-8db5-c78443fa1ad1</Old>
                <SDSU>d5e56cab-19a1-4d1f-aabc-eec6793cf439</SDSU>
                <Passwords>
                    <Professional>9fd118e5-c785-4b9b-a687-b06c65285e67</Professional>
                </Passwords>
            </Emails>
            <cPanel>
                <URL>https://rohancp.sdsu.edu:2083/cpanel</URL>
                <Username>dualpower</Username>
                <Password>960f933f-937f-409e-a9fa-f00d97586fcd</Password>
                <SSH_PW>266d3c1e-de41-475b-b169-bdd5d2518440</SSH_PW>
            </cPanel>
            <Hostinger>
                <URL></URL>
                <DatabaseURL></DatabaseURL>
                <SSHUsername></SSHUsername>
                <Password></Password>
            </Hostinger>
        </Object>
        
    </Objects>
</BrandonMFong>